nonebot_plugin_manga_translator/__init__.py
nonebot_plugin_manga_translator/config.py
nonebot_plugin_manga_translator/utils.py
nonebot_plugin_manga_translator-0.2.5.dist-info/LICENSE
nonebot_plugin_manga_translator-0.2.5.dist-info/METADATA
nonebot_plugin_manga_translator-0.2.5.dist-info/WHEEL
nonebot_plugin_manga_translator-0.2.5.dist-info/RECORD
