Metadata-Version: 2.3
Name: nonebot-plugin-manga-translator
Version: 0.2.5
Summary: 基于nonebot2的适配多种api的图片/漫画翻译插件
License: MIT
Author: xenophon
Author-email: 674550338@qq.com
Requires-Python: >=3.9,<4.0
Classifier: License :: OSI Approved :: MIT License
Classifier: Programming Language :: Python :: 3
Classifier: Programming Language :: Python :: 3.9
Classifier: Programming Language :: Python :: 3.10
Classifier: Programming Language :: Python :: 3.11
Classifier: Programming Language :: Python :: 3.12
Classifier: Programming Language :: Python :: 3.13
Requires-Dist: Pillow (>=10.0.0)
Requires-Dist: httpx (>=0.20.0,<1.0.0)
Requires-Dist: nonebot-plugin-alconna (>=0.40.1,<1.0.0)
Requires-Dist: nonebot2 (>=2.2.0,<3.0.0)
